pypiscout/SCout.py
pypiscout/SCout_Logger.py
pypiscout/SCout_helpers.py
pypiscout/__init__.py
pypiscout-2.0.3.dist-info/LICENSE
pypiscout-2.0.3.dist-info/METADATA
pypiscout-2.0.3.dist-info/WHEEL
pypiscout-2.0.3.dist-info/top_level.txt
pypiscout-2.0.3.dist-info/RECORD
