Metadata-Version: 2.1
Name: pypiscout
Version: 2.0.3
Summary: Description Special Character Out (aka pypiscout) | Prints uniformly formatted console output
Home-page: https://github.com/holzkohlengrill/SCout
Author: Marcel Schmalzl
License: MIT
Platform: UNKNOWN
Classifier: Programming Language :: Python :: 3
Classifier: License :: OSI Approved :: MIT License
Classifier: Operating System :: OS Independent
License-File: LICENSE
